jupyter_agent_toolkit/__init__.py
jupyter_agent_toolkit/py.typed
jupyter_agent_toolkit/kernel/__init__.py
jupyter_agent_toolkit/kernel/hooks.py
jupyter_agent_toolkit/kernel/manager.py
jupyter_agent_toolkit/kernel/messages.py
jupyter_agent_toolkit/kernel/mimetypes.py
jupyter_agent_toolkit/kernel/serialization.py
jupyter_agent_toolkit/kernel/session.py
jupyter_agent_toolkit/kernel/transport.py
jupyter_agent_toolkit/kernel/types.py
jupyter_agent_toolkit/kernel/variable_ops.py
jupyter_agent_toolkit/kernel/variables.py
jupyter_agent_toolkit/kernel/transports/local.py
jupyter_agent_toolkit/kernel/transports/server.py
jupyter_agent_toolkit/notebook/__init__.py
jupyter_agent_toolkit/notebook/cells.py
jupyter_agent_toolkit/notebook/config.py
jupyter_agent_toolkit/notebook/factory.py
jupyter_agent_toolkit/notebook/session.py
jupyter_agent_toolkit/notebook/transport.py
jupyter_agent_toolkit/notebook/types.py
jupyter_agent_toolkit/notebook/utils.py
jupyter_agent_toolkit/notebook/transports/__init__.py
jupyter_agent_toolkit/notebook/transports/contents.py
jupyter_agent_toolkit/notebook/transports/local_file.py
jupyter_agent_toolkit/notebook/transports/collab/__init__.py
jupyter_agent_toolkit/notebook/transports/collab/protocol.py
jupyter_agent_toolkit/notebook/transports/collab/transport.py
jupyter_agent_toolkit/notebook/transports/collab/yutils.py
jupyter_agent_toolkit/utils/__init__.py
jupyter_agent_toolkit/utils/execution.py
jupyter_agent_toolkit/utils/factories.py
jupyter_agent_toolkit/utils/outputs.py
jupyter_agent_toolkit/utils/packages.py
jupyter_agent_toolkit-0.1.12.dist-info/licenses/LICENSE
jupyter_agent_toolkit-0.1.12.dist-info/METADATA
jupyter_agent_toolkit-0.1.12.dist-info/WHEEL
jupyter_agent_toolkit-0.1.12.dist-info/top_level.txt
jupyter_agent_toolkit-0.1.12.dist-info/RECORD
