Metadata-Version: 2.4
Name: jupyter-agent-toolkit
Version: 0.1.12
Summary: A toolkit for building, managing, and extending Jupyter agent workflows, including kernel and notebook utilities.
Author-email: Roberto Rodriguez <9653181+Cyb3rWard0g@users.noreply.github.com>
License: MIT
Project-URL: Homepage, https://github.com/Cyb3rWard0g/jupyter-agent-toolkit
Project-URL: Repository, https://github.com/Cyb3rWard0g/jupyter-agent-toolkit
Project-URL: Issues, https://github.com/Cyb3rWard0g/jupyter-agent-toolkit/issues
Keywords: Jupyter,agents,kernels,notebooks,collaboration,data
Classifier: Programming Language :: Python :: 3
Classifier: Programming Language :: Python :: 3 :: Only
Classifier: Programming Language :: Python :: 3.11
Classifier: Programming Language :: Python :: 3.12
Classifier: Programming Language :: Python :: 3.13
Classifier: License :: OSI Approved :: MIT License
Classifier: Operating System :: OS Independent
Requires-Python: <3.14,>=3.11
License-File: LICENSE
Requires-Dist: jupyter-client>=8.6.3
Requires-Dist: numpy<2
Requires-Dist: nbformat>=5.10.4
Requires-Dist: pandas>=2.3.1
Requires-Dist: pyarrow>=21.0.0
Requires-Dist: aiohttp>=3.9
Requires-Dist: yarl>=1.9
Requires-Dist: pycrdt>=0.12.27
Requires-Dist: jupyter-core>=5.8.1
Requires-Dist: jupyter-ydoc>=3.1.0
Provides-Extra: dev
Requires-Dist: pytest>=8.4.2; extra == "dev"
Requires-Dist: pytest-asyncio>=0.23; extra == "dev"
Requires-Dist: anyio>=4; extra == "dev"
Requires-Dist: ipykernel; extra == "dev"
Requires-Dist: ruff>=0.6.0; extra == "dev"
Requires-Dist: black; extra == "dev"
Requires-Dist: build; extra == "dev"
Requires-Dist: twine; extra == "dev"
Requires-Dist: packaging; extra == "dev"
Requires-Dist: setuptools; extra == "dev"
Requires-Dist: setuptools_scm; extra == "dev"
Requires-Dist: wheel; extra == "dev"
Dynamic: license-file
